cudacanvas/__init__.py
cudacanvas/cudaGLStream.cpython-38-x86_64-linux-gnu.so
cudacanvas-2.2.2.post121.dist-info/LICENSE
cudacanvas-2.2.2.post121.dist-info/METADATA
cudacanvas-2.2.2.post121.dist-info/WHEEL
cudacanvas-2.2.2.post121.dist-info/top_level.txt
cudacanvas-2.2.2.post121.dist-info/RECORD
